{
  "$schema": "https://mintlify.com/docs.json",
  "theme": "mint",
  "name": "ZIPLIME",
  "colors": {
    "primary": "#CEFC31",
    "light": "#CEFC31",
    "dark": "#A6D91C"
  },
  "favicon": "/favicon.png",
  "navigation": {
    "tabs": [
      {
        "tab": "ZipLime Guide",
        "groups": [
          {
            "group": "Get Started",
            "pages": [
              "guide/getting-started/overview",
              "guide/getting-started/how-it-works",
              "guide/getting-started/registration"
            ]
          },
          {
            "group": "Platform",
            "pages": [
              "guide/platform/ai-agent-team",
              "guide/platform/three-levels",
              "guide/platform/product-features",
              "guide/platform/real-trading"
            ]
          },
          {
            "group": "Product",
            "pages": [
              "guide/product/two-environments",
              "guide/product/engine-and-technology",
              "guide/product/infrastructure-and-security",
              "guide/product/how-we-are-different"
            ]
          },
          {
            "group": "Plans & Events",
            "pages": [
              "guide/plans/pricing-and-registration"
            ]
          },
          {
            "group": "Resources",
            "pages": [
              "guide/resources/faq",
              "guide/resources/glossary"
            ]
          }
        ]
      },
      {
        "tab": "Backtesting Language",
        "groups": [
          {
            "group": "Introduction",
            "pages": [
              "language/introduction/engine-overview",
              "language/introduction/under-the-hood"
            ]
          },
          {
            "group": "Writing Strategies",
            "pages": [
              "language/writing-strategies/three-levels",
              "language/writing-strategies/timeframes-and-history",
              "language/writing-strategies/costs-and-commissions"
            ]
          },
          {
            "group": "Strategy Language",
            "pages": [
              "language/strategy-language/overview",
              "language/strategy-language/algorithm-file",
              "language/strategy-language/context-api",
              "language/strategy-language/market-data",
              "language/strategy-language/orders",
              "language/strategy-language/portfolio-and-recording",
              "language/strategy-language/scheduling-and-controls",
              "language/strategy-language/pipelines",
              "language/strategy-language/zipline-migration"
            ]
          },
          {
            "group": "Migrating to Ziplime",
            "pages": [
              "language/migrating/from-metatrader",
              "language/migrating/from-quik",
              "language/migrating/from-tradingview",
              "language/migrating/from-quantconnect",
              "language/migrating/from-zipline-quantopian"
            ]
          },
          {
            "group": "Limitations",
            "pages": [
              "language/limitations/not-for-hft"
            ]
          }
        ]
      }
    ],
  "global": {
      "anchors": [
      ]
    }
  },
  "navbar": {
    "links": [
      {
        "label": "Support",
        "href": "mailto:varbuzov@limex.com"
      }
    ],
    "primary": {
      "type": "button",
      "label": "Platform",
      "href": "https://ziplime.limex.com"
    }
  },
  "footer": {
    "socials": {
      "x": "https://x.com/limex",
      "github": "https://github.com/limex",
      "linkedin": "https://linkedin.com/company/limex"
    }
  },
  "background": {
    "decoration": "grid",
    "color": {
      "light": "#FFFFFF",
      "dark": "#0A0A0A"
    }
  },
  "fonts": {
    "family": "Archivo"
  },
  "appearance": {
    "default": "dark"
  }
}
